neptune_scale/__init__.py
neptune_scale/api/__init__.py
neptune_scale/api/run.py
neptune_scale/api/validation.py
neptune_scale/cli/__init__.py
neptune_scale/cli/commands.py
neptune_scale/cli/sync.py
neptune_scale/exceptions.py
neptune_scale/legacy.py
neptune_scale/logging/console_log_capture.py
neptune_scale/logging/logging_handler.py
neptune_scale/logging/logging_utils.py
neptune_scale/net/__init__.py
neptune_scale/net/api_client.py
neptune_scale/net/projects.py
neptune_scale/projects.py
neptune_scale/sync/__init__.py
neptune_scale/sync/errors_tracking.py
neptune_scale/sync/files.py
neptune_scale/sync/lag_tracking.py
neptune_scale/sync/metadata_splitter.py
neptune_scale/sync/operations_repository.py
neptune_scale/sync/parameters.py
neptune_scale/sync/size_util.py
neptune_scale/sync/storage/__init__.py
neptune_scale/sync/storage/azure_storage.py
neptune_scale/sync/storage/gcs.py
neptune_scale/sync/storage/s3.py
neptune_scale/sync/supervisor.py
neptune_scale/sync/sync_process.py
neptune_scale/types.py
neptune_scale/util/__init__.py
neptune_scale/util/daemon.py
neptune_scale/util/envs.py
neptune_scale/util/generate_run_id.py
neptune_scale/util/logger.py
neptune_scale/util/source_tracking.py
neptune_scale/util/styles.py
neptune_scale/util/timer.py
neptune_scale/vendor/__init__.py
neptune_scale/vendor/lib_programname.py
neptune_scale-0.29.0.dist-info/METADATA
neptune_scale-0.29.0.dist-info/WHEEL
neptune_scale-0.29.0.dist-info/entry_points.txt
neptune_scale-0.29.0.dist-info/RECORD
