Metadata-Version: 2.4
Name: neptune-scale
Version: 0.29.0
Summary: A minimal client library
License: Apache-2.0
Keywords: MLOps,ML Experiment Tracking,ML Model Registry,ML Model Store,ML Metadata Store
Author: neptune.ai
Author-email: contact@neptune.ai
Requires-Python: >=3.9,<4.0
Classifier: Development Status :: 4 - Beta
Classifier: Environment :: Console
Classifier: Intended Audience :: Developers
Classifier: Intended Audience :: Science/Research
Classifier: License :: OSI Approved :: Apache Software License
Classifier: Natural Language :: English
Classifier: Operating System :: MacOS
Classifier: Operating System :: Microsoft :: Windows
Classifier: Operating System :: POSIX
Classifier: Operating System :: Unix
Classifier: Programming Language :: Python :: 3
Classifier: Programming Language :: Python :: 3.9
Classifier: Programming Language :: Python :: 3.10
Classifier: Programming Language :: Python :: 3.11
Classifier: Programming Language :: Python :: 3.12
Classifier: Programming Language :: Python :: 3.13
Classifier: Programming Language :: Python :: 3.14
Classifier: Topic :: Scientific/Engineering :: Artificial Intelligence
Classifier: Topic :: Software Development :: Libraries :: Python Modules
Requires-Dist: GitPython (>=2.0.8)
Requires-Dist: aiofiles (>=22.1.0)
Requires-Dist: azure-storage-blob (>=12.7.0,<13.0.0)
Requires-Dist: backoff (>=2.0.0,<3.0.0)
Requires-Dist: click (>=7.0)
Requires-Dist: filetype (>=1.2.0,<2.0.0)
Requires-Dist: more-itertools (>=10.0.0,<11.0.0)
Requires-Dist: neptune-api (>=0.23.0,<0.24.0)
Requires-Dist: psutil (>=5.0.0)
Requires-Dist: requests (>=2.21.0)
Requires-Dist: tqdm (>=4.21.0,<5.0.0)
Project-URL: Documentation, https://docs.neptune.ai/
Project-URL: Repository, https://github.com/neptune-ai/neptune-client-scale
Project-URL: Tracker, https://github.com/neptune-ai/neptune-client-scale/issues
